setup.py
bdl/__init__.py
bdl.egg-info/PKG-INFO
bdl.egg-info/SOURCES.txt
bdl.egg-info/dependency_links.txt
bdl.egg-info/top_level.txt
bdl.egg-info/zip-safe
test/test_returns.py