Metadata-Version: 1.0
Name: bdl
Version: 0.0.0
Summary: Bondage and Discipline, Python style.
Home-page: http://github.com/adamdeprince/bdl
Author: Adam DePrince
Author-email: adeprince@nypublicradio.org
License: Apache
Platform: UNKNOWN
Classifier: Intended Audience :: Developers
Classifier: Topic :: Software Development
